{
    "imageReference": "/assets/icons/GoddardLogo_White-Web.png",
    "logoAltText": "GSL Logo",
    "links": [
        {
            "newTab": "true",
            "link": "/about",
            "linkText": "About Us",
            "targetUrl": "/about"
        },
        {
            "newTab": "true",
            "link": "https://recruiting.ultipro.com/GOD1001GOSY/JobBoard/d9bcba70-21be-405b-a68e-7fb1d8cb196c",
            "linkText": "Careers at GSL",
            "targetUrl": "https://recruiting.ultipro.com/GOD1001GOSY/JobBoard/d9bcba70-21be-405b-a68e-7fb1d8cb196c"
        },
        {
            "newTab": "true",
            "link": "/news",
            "linkText": "News",
            "targetUrl": "/news"
        },
        {
            "newTab": "true",
            "link": "/locations",
            "linkText": "School Locations",
            "targetUrl": "/locations"
        },
        {
            "newTab": "true",
            "link": "/executive-leadership",
            "linkText": "Goddard Leadership",
            "targetUrl": "/executive-leadership"
        },
        {
            "newTab": "true",
            "link": "https://familyconnect.goddardschool.com/Login.aspx",
            "linkText": "Family Connect",
            "targetUrl": "https://familyconnect.goddardschool.com/Login.aspx"
        },
        {
            "newTab": "true",
            "link": "/frequently-asked-questions",
            "linkText": "FAQs",
            "targetUrl": "/frequently-asked-questions"
        },
        {
            "newTab": "true",
            "link": "/contact",
            "linkText": "Contact Us",
            "targetUrl": "/contact"
        },
        {
            "newTab": "true",
            "link": "/sitemap",
            "linkText": "Site Map",
            "targetUrl": "/sitemap"
        },
        {
            "newTab": "true",
            "link": "http://www.goddardschoolfranchise.com",
            "linkText": "Franchising",
            "targetUrl": "http://www.goddardschoolfranchise.com"
        }
    ],
    "socialIconsTitle": "CONNECT WITH US!",
    "socialIconList": [
        {
            "isEnabled": "true",
            "targetUrl": "https://www.facebook.com/goddardschool",
            "newTab": "true",
            "imageReference": "/assets/icons/social-media-icon-facebook.svg",
            "linkText": ""
        },
        {
            "isEnabled": "true",
            "targetUrl": "https://www.instagram.com/goddard_school/",
            "newTab": "true",
            "imageReference": "/assets/icons/social-media-icon-instagram.svg",
            "linkText": ""
        },
        {
            "isEnabled": "true",
            "targetUrl": "https://www.youtube.com/user/goddardschool",
            "newTab": "true",
            "imageReference": "/assets/icons/social-media-icon-youtube.svg",
            "linkText": ""
        }
    ],
    "copyright": "© 2024 Goddard Franchisor LLC",
    "legalLinksList": [
        {
            "targetUrl": "/",
            "newTab": "false",
            "linkText": "Privacy Policy"
        },
        {
            "targetUrl": "/terms-and-conditions",
            "newTab": "false",
            "linkText": "Terms & Conditions"
        },
        {
            "targetUrl": "#OneTrustToggle",
            "newTab": "false",
            "linkText": "Cookie Management"
        },
        {
            "targetUrl": "/rights-request-form",
            "newTab": "false",
            "linkText": "Do Not Sell or Share My Personal Information"
        }
    ],
    "footerTopIconText": ""
}